setup.py
libre_crawler.egg-info/.DS_Store
libre_crawler.egg-info/PKG-INFO
libre_crawler.egg-info/SOURCES.txt
libre_crawler.egg-info/dependency_links.txt
libre_crawler.egg-info/not-zip-safe
libre_crawler.egg-info/requires.txt
libre_crawler.egg-info/top_level.txt
librecrawler/__init__.py
librecrawler/crawler.py