Metadata-Version: 1.0
Name: libre-crawler
Version: 0.1
Summary: Generic web crawler for stock photo websites
Home-page: http://github.com/davegri/libre-crawler
Author: David Griver
Author-email: dgriver@gmail.com
License: MIT
Platform: UNKNOWN
